<?xml version="1.0" encoding="UTF-8"?>

<beans	xmlns="http://www.springframework.org/schema/beans"
		xmlns:sec="http://www.springframework.org/schema/security"
		xmlns:xsi="http://www.w3.org/2001/XMLSchema-instance"
		xsi:schemaLocation="
				http://www.springframework.org/schema/beans
				http://www.springframework.org/schema/beans/spring-beans.xsd
				http://www.springframework.org/schema/security
				http://www.springframework.org/schema/security/spring-security.xsd">

	<sec:http create-session="never" use-expressions="true" auto-config="true" entry-point-ref="preAuthenticatedProcessingFilterEntryPoint">
		<sec:intercept-url pattern="/services/*" access="isAnonymous()"/>
		<sec:intercept-url pattern="/ws/*" access="isAnonymous()"/>
		<sec:intercept-url pattern="/scspRouting/*" access="isAnonymous()"/>
		<sec:intercept-url pattern="/error" access="isAnonymous()"/>
		<sec:intercept-url pattern="/servei/*/permis" access="hasRole('EMS_ADMIN')"/>
		<sec:intercept-url pattern="/servei/*/create" access="hasRole('EMS_ADMIN')"/>
		<sec:intercept-url pattern="/servei/*/delete" access="hasRole('EMS_ADMIN')"/>
		<sec:intercept-url pattern="/**" access="hasRole('EMS_ADMIN') or hasRole('EMS_RESP')"/>
		<sec:custom-filter position="PRE_AUTH_FILTER" ref="preauthFilter"/>
		<sec:anonymous/>
		<sec:session-management session-fixation-protection="none"/>
	</sec:http>

	<sec:authentication-manager alias="authenticationManager">
		<sec:authentication-provider ref="preAuthenticatedAuthenticationProvider"/>
	</sec:authentication-manager>

	<bean id="preAuthenticatedProcessingFilterEntryPoint" class="org.springframework.security.web.authentication.Http403ForbiddenEntryPoint" />
	<bean id="preAuthenticatedAuthenticationProvider" class="org.springframework.security.web.authentication.preauth.PreAuthenticatedAuthenticationProvider">
		<property name="preAuthenticatedUserDetailsService">
			<bean class="org.springframework.security.web.authentication.preauth.PreAuthenticatedGrantedAuthoritiesUserDetailsService" />
		</property>
	</bean>

	<bean id="preauthFilter" class="org.springframework.security.web.authentication.preauth.j2ee.J2eePreAuthenticatedProcessingFilter">
		<property name="authenticationDetailsSource">
			<bean class="es.caib.emiserv.war.security.RolesBasedPreAuthenticatedWebAuthenticationDetailsSource">
				<property name="mappableRolesRetriever">
					<bean class="es.caib.emiserv.war.security.RolesBasedMappableAttributesRetriever">
						<property name="defaultMappableAttributes">
							<set>
								<value>EMS_ADMIN</value>
								<value>EMS_RESP</value>
							</set>
						</property>
					</bean>
				</property>
				<property name="userRoles2GrantedAuthoritiesMapper">
					<bean class="es.caib.emiserv.war.security.RolesBasedAttributes2GrantedAuthoritiesMapper"/>
				</property>
			</bean>
		</property>
		<property name="authenticationManager" ref="authenticationManager"/>
	</bean>

	<bean class="org.springframework.security.web.access.expression.DefaultWebSecurityExpressionHandler"/>
	<bean class="es.caib.emiserv.war.security.DefaultRolesPrefixPostProcessor"/>

</beans>